aliyunsdkbpstudio/__init__.py
aliyunsdkbpstudio/request/__init__.py
aliyunsdkbpstudio/request/v20210931/AppFailBackRequest.py
aliyunsdkbpstudio/request/v20210931/AppFailOverRequest.py
aliyunsdkbpstudio/request/v20210931/ChangeResourceGroupRequest.py
aliyunsdkbpstudio/request/v20210931/CreateApplicationRequest.py
aliyunsdkbpstudio/request/v20210931/DeleteApplicationRequest.py
aliyunsdkbpstudio/request/v20210931/DeployApplicationRequest.py
aliyunsdkbpstudio/request/v20210931/ExecuteOperationASyncRequest.py
aliyunsdkbpstudio/request/v20210931/ExecuteOperationSyncRequest.py
aliyunsdkbpstudio/request/v20210931/GetApplicationRequest.py
aliyunsdkbpstudio/request/v20210931/GetApplicationVariables4FailRequest.py
aliyunsdkbpstudio/request/v20210931/GetApplicationVariablesRequest.py
aliyunsdkbpstudio/request/v20210931/GetExecuteOperationResultRequest.py
aliyunsdkbpstudio/request/v20210931/GetFoTaskStatusRequest.py
aliyunsdkbpstudio/request/v20210931/GetPotentialFailZonesRequest.py
aliyunsdkbpstudio/request/v20210931/GetResource4ModifyRecordRequest.py
aliyunsdkbpstudio/request/v20210931/GetResult4QueryInstancePrice4ModifyRequest.py
aliyunsdkbpstudio/request/v20210931/GetTemplateRequest.py
aliyunsdkbpstudio/request/v20210931/GetTokenRequest.py
aliyunsdkbpstudio/request/v20210931/InitAppFailOverRequest.py
aliyunsdkbpstudio/request/v20210931/ListApplicationRequest.py
aliyunsdkbpstudio/request/v20210931/ListFoCreatedAppsRequest.py
aliyunsdkbpstudio/request/v20210931/ListTagResourcesRequest.py
aliyunsdkbpstudio/request/v20210931/ListTemplateRequest.py
aliyunsdkbpstudio/request/v20210931/ModifyApplicationSpecRequest.py
aliyunsdkbpstudio/request/v20210931/QueryInstancePrice4ModifyRequest.py
aliyunsdkbpstudio/request/v20210931/QueryInstanceSpec4ModifyRequest.py
aliyunsdkbpstudio/request/v20210931/ReConfigApplicationRequest.py
aliyunsdkbpstudio/request/v20210931/ReleaseApplicationRequest.py
aliyunsdkbpstudio/request/v20210931/ValidateApplicationRequest.py
aliyun_python_sdk_bpstudio-1.0.18.dist-info/LICENSE
aliyun_python_sdk_bpstudio-1.0.18.dist-info/METADATA
aliyun_python_sdk_bpstudio-1.0.18.dist-info/WHEEL
aliyun_python_sdk_bpstudio-1.0.18.dist-info/top_level.txt
aliyun_python_sdk_bpstudio-1.0.18.dist-info/RECORD
